fastapi_inject/__init__.py
fastapi_inject/_exceptions.py
fastapi_inject/enable.py
fastapi_inject/injection.py
fastapi_inject/py.typed
fastapi_inject/utils.py
fastapi_inject-0.4.3.dist-info/LICENSE
fastapi_inject-0.4.3.dist-info/METADATA
fastapi_inject-0.4.3.dist-info/WHEEL
fastapi_inject-0.4.3.dist-info/RECORD
